MANIFEST.in
README.rst
setup.py
factorialLYL.egg-info/PKG-INFO
factorialLYL.egg-info/SOURCES.txt
factorialLYL.egg-info/dependency_links.txt
factorialLYL.egg-info/top_level.txt
myfact/__init__.py
myfact/fact.py