Metadata-Version: 1.0
Name: factorialLYL
Version: 0.1
Summary: Factorial module
Home-page: http://www.shiyanlou.com.courses/596
Author: LYL
Author-email: dalongxiabj@163.com
License: MIT
Platform: Linux
